qsketchmetric/__init__.py
qsketchmetric/renderer.py
qsketchmetric/semiautomatic.py
tests/__init__.py
tests/test_renderer.py
tests/test_semiautomatic.py
qsketchmetric-1.7.2.dist-info/LICENSE
qsketchmetric-1.7.2.dist-info/METADATA
qsketchmetric-1.7.2.dist-info/WHEEL
qsketchmetric-1.7.2.dist-info/top_level.txt
qsketchmetric-1.7.2.dist-info/RECORD
