Metadata-Version: 2.1
Name: qsketchmetric
Version: 1.7.2
Summary: Python 2D parametric DXF rendering engine.
Home-page: https://github.com/MadScrewdriver/qsketchmetric
Author: Franciszek Łajszczak
Author-email: franciszek@lajszczak.dev
License: MIT
Project-URL: Documentation, https://qsketchmetric.readthedocs.io/
Keywords: CAD,QCAD,2D,parametric,drawing,renderer,python renderer,python CAD,python 2d CAD,ppython 2d drawing,python parametric drawing,python parametric CAD,python QCAD,QCAD python,parametric QCAD python,parametric QCAD,QCAD parametric,QCAD python parametric,QCAD python 2d,
Classifier: Development Status :: 3 - Alpha
Classifier: Intended Audience :: Developers
Classifier: Topic :: Software Development :: Libraries
Classifier: License :: OSI Approved :: MIT License
Classifier: Programming Language :: Python :: 3.11
Classifier: Programming Language :: Python :: 3.10
Classifier: Programming Language :: Python :: 3.9
Requires-Python: >=3.9
License-File: LICENSE
Requires-Dist: ezdxf
Requires-Dist: py-expression-eval
Requires-Dist: pyparsing
Requires-Dist: typing-extensions
